kaw/__init__.py
kaw/kaw.py
kaw/listed_companies_info.py
wak-1.0.dist-info/METADATA
wak-1.0.dist-info/WHEEL
wak-1.0.dist-info/top_level.txt
wak-1.0.dist-info/RECORD
